dLuxToliman/__init__.py
dLuxToliman/diffractive_pupil.npy
dLuxToliman/gradient_energy.py
dLuxToliman/instruments.py
dLuxToliman/optical_layers.py
dLuxToliman/optical_systems.py
dLuxToliman/optics.py
dLuxToliman/sources.py
dLuxToliman/telescopes.py
dLuxToliman/layers/__init__.py
dLuxToliman/layers/detector_layers.py
dLuxToliman/layers/optical_layers.py
dLuxToliman-0.3.0.dist-info/LICENSE
dLuxToliman-0.3.0.dist-info/METADATA
dLuxToliman-0.3.0.dist-info/WHEEL
dLuxToliman-0.3.0.dist-info/top_level.txt
dLuxToliman-0.3.0.dist-info/RECORD
