Metadata-Version: 2.1
Name: dLuxToliman
Version: 0.3.0
Summary: A repo to hold the canonical dLux Toliman models.
Home-page: https://github.com/maxecharles/dLuxToliman
Author: Max Charles
Author-email: max.charles@sydney.edu.au
Project-URL: Bug Tracker, https://github.com/maxecharles/dLuxToliman/issues
Classifier: Programming Language :: Python :: 3
Classifier: Operating System :: OS Independent
Requires-Python: >=3.7,<4.0
License-File: LICENSE
Requires-Dist: dLux (==0.14.*)
Requires-Dist: zodiax
